oauth2_xfel_client/__init__.py
oauth2_xfel_client/oauth2_client_backend.py
oauth2_xfel_client/tests/__init__.py
oauth2_xfel_client/tests/oauth2_client_backend_test.py
oauth2_xfel_client-6.1.1.dist-info/AUTHORS.rst
oauth2_xfel_client-6.1.1.dist-info/LICENSE
oauth2_xfel_client-6.1.1.dist-info/METADATA
oauth2_xfel_client-6.1.1.dist-info/WHEEL
oauth2_xfel_client-6.1.1.dist-info/top_level.txt
oauth2_xfel_client-6.1.1.dist-info/RECORD
