Metadata-Version: 2.1
Name: oauth2-xfel-client
Version: 6.1.1
Summary: Python OAUTH 2.0 generic Client used for Backend Application strategy authentication on European XFEL Web Applications
Home-page: https://git.xfel.eu/gitlab/ITDM/oauth2_xfel_client
Author: Luís Maia
Author-email: luis.maia@xfel.eu
Maintainer: Luís Maia, Thomas Kluyver
Maintainer-email: luis.maia@xfel.eu, thomas.kluyver@xfel.eu
License: MIT
Platform: any
Classifier: Development Status :: 5 - Production/Stable
Classifier: Environment :: Web Environment
Classifier: Environment :: Console
Classifier: Intended Audience :: Developers
Classifier: Intended Audience :: Science/Research
Classifier: Natural Language :: English
Classifier: License :: OSI Approved :: MIT License
Classifier: Programming Language :: Python
Classifier: Programming Language :: Python :: 3
Classifier: Operating System :: OS Independent
Classifier: Topic :: Scientific/Engineering :: Information Analysis
Classifier: Topic :: Software Development :: Libraries :: Python Modules
Requires-Python: >=3.7
License-File: LICENSE
License-File: AUTHORS.rst
Requires-Dist: oauthlib
Requires-Dist: requests
Requires-Dist: requests-oauthlib
Requires-Dist: pytz
Provides-Extra: test
Requires-Dist: pytest ; extra == 'test'
Requires-Dist: pytest-cov ; extra == 'test'
Requires-Dist: python-dateutil ; extra == 'test'
Requires-Dist: pytz ; extra == 'test'
Requires-Dist: pycodestyle ; extra == 'test'
Requires-Dist: freezegun ; extra == 'test'
